{
  "totalRowsScanned": 2079,
  "finalWordCount": 1795,
  "added": 1795,
  "replacedOrMerged": 283,
  "rejected": 1,
  "domainCounts": {
    "people": 12,
    "daily-object": 17,
    "technology": 39,
    "grammar": 37,
    "daily": 148,
    "description": 19,
    "market-transport": 23,
    "chat": 109,
    "governance": 52,
    "phrases": 21,
    "generated-chat-phrases": 40,
    "chat-phrase": 51,
    "pronoun": 10,
    "daily-chat": 30,
    "travel": 5,
    "food": 34,
    "health": 27,
    "manipur-places": 12,
    "school": 17,
    "mixed-english": 61,
    "book-writing": 19,
    "writing": 58,
    "time-schedule": 16,
    "daily-actions": 24,
    "time": 16,
    "emotion-social": 24,
    "verb": 532,
    "nature": 7,
    "nature-weather": 21,
    "place-name": 15,
    "place": 30,
    "number": 15,
    "question": 11,
    "generated-candidate": 119,
    "objects-places": 14,
    "descriptions": 13,
    "body": 9,
    "daily-place": 32,
    "school-writing": 15,
    "commerce": 1,
    "family": 11,
    "digital-chat": 9,
    "relation": 3,
    "people-relations": 15,
    "concept": 1,
    "translation": 1
  },
  "levelCounts": {
    "chat": 1607,
    "formal": 178,
    "editorial": 10
  },
  "reviewCounts": {
    "needs_review": 1795
  },
  "imports": [
    "build10-chat-governance-growth.csv",
    "build10-expanded-candidate-batch.csv",
    "build11-database-explorer-growth.csv",
    "build12-daily-chat-article-growth.csv",
    "build8-candidate-lexicon.csv",
    "build9-user-and-chat-expansion.csv",
    "seed-master-lexicon.csv"
  ]
}
